turbulette/__init__.py
turbulette/apps/__init__.py
turbulette/apps/app.py
turbulette/apps/auth/__init__.py
turbulette/apps/auth/core.py
turbulette/apps/auth/decorators.py
turbulette/apps/auth/directives.py
turbulette/apps/auth/exceptions.py
turbulette/apps/auth/graphql/queries/auth.graphql
turbulette/apps/auth/graphql/types/auth.graphql
turbulette/apps/auth/models.py
turbulette/apps/auth/policy/__init__.py
turbulette/apps/auth/policy/base.py
turbulette/apps/auth/policy/constants.py
turbulette/apps/auth/policy/policy.py
turbulette/apps/auth/pyd_models.py
turbulette/apps/auth/resolvers/policy.py
turbulette/apps/auth/resolvers/queries/token.py
turbulette/apps/auth/settings.py
turbulette/apps/auth/utils.py
turbulette/apps/base/__init__.py
turbulette/apps/base/graphql/base_schema.graphql
turbulette/apps/base/resolvers/root_types.py
turbulette/apps/base/settings.py
turbulette/apps/constants.py
turbulette/apps/exceptions.py
turbulette/apps/registry.py
turbulette/asgi.py
turbulette/cache.py
turbulette/conf/__init__.py
turbulette/conf/constants.py
turbulette/conf/exceptions.py
turbulette/conf/utils.py
turbulette/db/__init__.py
turbulette/db/database.py
turbulette/db/exceptions.py
turbulette/errors.py
turbulette/exceptions.py
turbulette/extensions.py
turbulette/main.py
turbulette/management/alembic_env.py
turbulette/management/cli.py
turbulette/management/templates/app/graphql/.gitkeep
turbulette/management/templates/app/models.py
turbulette/management/templates/app/resolvers/.gitkeep
turbulette/management/templates/project/.env
turbulette/management/templates/project/alembic/env.py
turbulette/management/templates/project/alembic/script.py.mako
turbulette/management/templates/project/alembic.ini
turbulette/management/templates/project/app.py
turbulette/management/templates/project/settings.py
turbulette/middleware/csrf.py
turbulette/routes.py
turbulette/test/pytest_plugin.py
turbulette/test/tester.py
turbulette/type/__init__.py
turbulette/type/definition.py
turbulette-0.5.1.dist-info/entry_points.txt
turbulette-0.5.1.dist-info/LICENSE
turbulette-0.5.1.dist-info/WHEEL
turbulette-0.5.1.dist-info/METADATA
turbulette-0.5.1.dist-info/RECORD
