Metadata-Version: 2.1
Name: turbulette
Version: 0.5.1
Summary: A batteries-included framework to build high performance, async GraphQL APIs
Home-page: https://github.com/turbulette/turbulette/
License: BSD-3-Clause
Keywords: grapql,api,asyncio,gino,ariadne
Author: Matthieu MN
Author-email: matthieu.macnab@pm.me
Maintainer: Matthieu MN
Maintainer-email: matthieu.macnab@pm.me
Requires-Python: >=3.6,<4.0
Classifier: Development Status :: 4 - Beta
Classifier: Intended Audience :: Developers
Classifier: License :: OSI Approved :: BSD License
Classifier: Natural Language :: English
Classifier: Operating System :: OS Independent
Classifier: Programming Language :: Python
Classifier: Programming Language :: Python :: 3
Classifier: Programming Language :: Python :: 3.6
Classifier: Programming Language :: Python :: 3.7
Classifier: Programming Language :: Python :: 3.8
Classifier: Programming Language :: Python :: 3.9
Classifier: Topic :: Internet :: WWW/HTTP
Classifier: Topic :: Software Development :: Libraries :: Application Frameworks
Classifier: Typing :: Typed
Provides-Extra: argon2
Provides-Extra: dev_doc
Provides-Extra: dev_lint
Provides-Extra: dev_profiling
Provides-Extra: dev_test
Requires-Dist: alembic (>=1.4.2,<2.0.0)
Requires-Dist: argon2-cffi (>=20.1.0,<21.0.0); extra == "argon2"
Requires-Dist: ariadne (>=0.11,<0.13)
Requires-Dist: async-asgi-testclient (>=1.4.5,<2.0.0); extra == "dev_test"
Requires-Dist: async-caches (>=0.3.0,<0.4.0)
Requires-Dist: black (>=20.8b1,<21.0); extra == "dev_lint"
Requires-Dist: ciso8601 (>=2.1.3,<3.0.0)
Requires-Dist: click (>=7.1.2,<8.0.0)
Requires-Dist: coverage[toml] (>=5.3,<6.0); extra == "dev_test"
Requires-Dist: gino[starlette] (>=1.0.1,<2.0.0)
Requires-Dist: memory_profiler (>=0.58.0,<0.59.0); extra == "dev_profiling"
Requires-Dist: mkdocs-git-revision-date-plugin (>=0.3,<0.4); extra == "dev_doc"
Requires-Dist: mkdocs-material (>=6.0.1,<7.0.0); extra == "dev_doc"
Requires-Dist: mkdocstrings (>=0.14.0,<0.15.0); extra == "dev_doc"
Requires-Dist: passlib[bcrypt] (>=1.7.2,<2.0.0)
Requires-Dist: prospector[with_bandit,with_mypy] (>=1.3.1,<2.0.0); extra == "dev_lint"
Requires-Dist: psycopg2 (>=2.8.5,<3.0.0)
Requires-Dist: pydantic[email] (>=1.6.1,<2.0.0)
Requires-Dist: pygments-graphql-lexer (>=0.1.0,<0.2.0); extra == "dev_doc"
Requires-Dist: pylint-pytest (>=0.3.0,<0.4.0); extra == "dev_lint"
Requires-Dist: pymdown-extensions (>=8.0.1,<9.0.0); extra == "dev_doc"
Requires-Dist: pytest (>=6.2.1,<7.0.0); extra == "dev_test"
Requires-Dist: pytest-asyncio (>=0.14.0,<0.15.0); extra == "dev_test"
Requires-Dist: pytest-cov (>=2.11.1,<3.0.0); extra == "dev_test"
Requires-Dist: python-jwt (>=3.2.6,<4.0.0)
Requires-Dist: python-multipart (>=0.0.5,<0.0.6); extra == "dev_test"
Requires-Dist: simple-settings (>=0.19.1,<1.1.0)
Requires-Dist: tuna (>=0.5.0,<0.6.0); extra == "dev_profiling"
Project-URL: Ariadne, https://ariadnegraphql.org/
Project-URL: Alembic, https://alembic.sqlalchemy.org/en/latest/
Project-URL: Documentation, https://turbulette.github.io/turbulette/
Project-URL: GINO, https://python-gino.org/docs/en/master/index.html
Project-URL: Pydantic, https://pydantic-docs.helpmanual.io/
Project-URL: Repository, https://github.com/turbulette/turbulette/
Project-URL: Starlette, https://www.starlette.io/
